setup.cfg
setup.py
roetsjbaan/__init__.py
roetsjbaan/datatypes.py
roetsjbaan/main.py
roetsjbaan/messages.py
roetsjbaan/migrator.py
roetsjbaan/versioner.py
roetsjbaan.egg-info/PKG-INFO
roetsjbaan.egg-info/SOURCES.txt
roetsjbaan.egg-info/dependency_links.txt
roetsjbaan.egg-info/entry_points.txt
roetsjbaan.egg-info/not-zip-safe
roetsjbaan.egg-info/requires.txt
roetsjbaan.egg-info/top_level.txt