Metadata-Version: 1.1
Name: roetsjbaan
Version: 0.1.4
Summary: A minimal, lightweight migration system
Home-page: https://github.com/mivdnber/roetsjbaan
Author: Michiel Van den Berghe
Author-email: michiel.vdb@gmail.com
License: MIT
Download-URL: https://github.com/mivdnber/roetsjbaan/tarball/0.1.4
Keywords: migration,database
Platform: UNKNOWN
